{
  "summary": [
    {
      "alias": "S1",
      "type": "Mutations",
      "names": ["Bladder", "High impact", "Muse"],
      "total": 8789
    },
    {
      "alias": "S2",
      "type": "Mutations",
      "names": ["Bladder", "High impact", "Mutect2"],
      "total": 10000
    },
    {
      "alias": "S3",
      "type": "Mutations",
      "names": ["Bladder", "High impact", "Varscan2"],
      "total": 10000
    }
  ],
  "set_operations": [
    {
      "S1_minus_S2_union_S3": {
        "data": {
          "viewer": {
            "explore": {
              "ssms": {
                "hits": {
                  "total": 688
                }
              }
            }
          }
        }
      }
    },
    {
      "S1_intersect_S3_minus_S2": {
        "data": {
          "viewer": {
            "explore": {
              "ssms": {
                "hits": {
                  "total": 1561
                }
              }
            }
          }
        }
      }
    },
    {
      "S1_intersect_S2_minus_S3": {
        "data": {
          "viewer": {
            "explore": {
              "ssms": {
                "hits": {
                  "total": 508
                }
              }
            }
          }
        }
      }
    },
    {
      "S1_intersect_S2_intersect_S3": {
        "data": {
          "viewer": {
            "explore": {
              "ssms": {
                "hits": {
                  "total": 6032
                }
              }
            }
          }
        }
      }
    },
    {
      "S3_minus_S1_union_S2": {
        "data": {
          "viewer": {
            "explore": {
              "ssms": {
                "hits": {
                  "total": 685
                }
              }
            }
          }
        }
      }
    },
    {
      "S2_intersect_S3_minus_S1": {
        "data": {
          "viewer": {
            "explore": {
              "ssms": {
                "hits": {
                  "total": 1722
                }
              }
            }
          }
        }
      }
    },
    {
      "S2_minus_S1_union_S3": {
        "data": {
          "viewer": {
            "explore": {
              "ssms": {
                "hits": {
                  "total": 1738
                }
              }
            }
          }
        }
      }
    }
  ]
}
